{"3QTK9dG0ETlZXC89GsUZyQ==":"1-2000x1003.jpg","vCU3RlvCgCfWade5pkhU9w==":"2-2000x1335.jpg","bvNzsTDvFb4+6cIPRZNGtQ==":"mbr-2000x3000.jpg","0McybbrNoZrm5yA0jvePPg==":"mbr-2000x2995.jpg","+qb3SSsIXKQHoXBx2KYg7w==":"3-2000x1500.jpg","spXc7r3UXhIzR0zbyurzoQ==":"3-2000x1126.jpg","yyfNs+trSDpXOkbE0arpnQ==":"4-2000x1500.jpg","mMLmClr7C0yu8bp7wWxixg==":"%E0%B8%99%E0%B8%81%E0%B8%9F%E0%B8%A5%E0%B8%B2%E0%B8%A1%E0%B8%B4%E0%B8%87%E0%B9%82%E0%B8%81-2000x1334.jpg","dWT2Od0fYORYomZHvXVuUQ==":"%E0%B9%81%E0%B8%9E%E0%B8%99%E0%B8%94%E0%B9%89%E0%B8%B2%E0%B8%A2%E0%B8%B1%E0%B8%81%E0%B8%A9%E0%B9%8C-2000x1337.jpg","CdcZPoLBfc71dbgzV9vkeg==":"4-1400x980.jpg","thWWuwYQl6Tj5Krgxhtflg==":"4-2000x1400.jpg","lINxtSVO8BXnzznw0Kq+Qg==":"5-2000x1125.jpg"}